mistral_tempest_tests/README.rst
mistral_tempest_tests/__init__.py
mistral_tempest_tests/config.py
mistral_tempest_tests/plugin.py
mistral_tempest_tests/services/__init__.py
mistral_tempest_tests/services/base.py
mistral_tempest_tests/services/v2/__init__.py
mistral_tempest_tests/services/v2/mistral_client.py
mistral_tempest_tests/tests/__init__.py
mistral_tempest_tests/tests/base.py
mistral_tempest_tests/tests/ssh_utils.py
mistral_tempest_tests/tests/utils.py
mistral_tempest_tests/tests/api/__init__.py
mistral_tempest_tests/tests/api/v2/__init__.py
mistral_tempest_tests/tests/api/v2/test_action_executions.py
mistral_tempest_tests/tests/api/v2/test_actions.py
mistral_tempest_tests/tests/api/v2/test_cron_triggers.py
mistral_tempest_tests/tests/api/v2/test_event_triggers.py
mistral_tempest_tests/tests/api/v2/test_executions.py
mistral_tempest_tests/tests/api/v2/test_services.py
mistral_tempest_tests/tests/api/v2/test_tasks.py
mistral_tempest_tests/tests/api/v2/test_workbooks.py
mistral_tempest_tests/tests/api/v2/test_workflows.py
mistral_tempest_tests/tests/resources/action_v2.yaml
mistral_tempest_tests/tests/resources/single_wf.yaml
mistral_tempest_tests/tests/resources/wb_v1.yaml
mistral_tempest_tests/tests/resources/wb_v2.yaml
mistral_tempest_tests/tests/resources/wb_with_nested_wf.yaml
mistral_tempest_tests/tests/resources/wf_action_ex_concurrency.yaml
mistral_tempest_tests/tests/resources/wf_task_ex_concurrency.yaml
mistral_tempest_tests/tests/resources/wf_v2.yaml
mistral_tempest_tests/tests/resources/for_wf_namespace/lowest_level_wf.yaml
mistral_tempest_tests/tests/resources/for_wf_namespace/middle_wf.yaml
mistral_tempest_tests/tests/resources/for_wf_namespace/top_level_wf.yaml
mistral_tempest_tests/tests/resources/openstack/action_collection_wb.yaml
mistral_tempest_tests/tests/scenario/__init__.py
mistral_tempest_tests/tests/scenario/engine/__init__.py
mistral_tempest_tests/tests/scenario/engine/actions/__init__.py
mistral_tempest_tests-2.7.0.dist-info/AUTHORS
mistral_tempest_tests-2.7.0.dist-info/LICENSE
mistral_tempest_tests-2.7.0.dist-info/METADATA
mistral_tempest_tests-2.7.0.dist-info/WHEEL
mistral_tempest_tests-2.7.0.dist-info/entry_points.txt
mistral_tempest_tests-2.7.0.dist-info/pbr.json
mistral_tempest_tests-2.7.0.dist-info/top_level.txt
mistral_tempest_tests-2.7.0.dist-info/RECORD
