Metadata-Version: 2.1
Name: mistral_tempest_tests
Version: 2.7.0
Summary: Tempest plugin for Mistral project
Author-email: OpenStack <openstack-discuss@lists.openstack.org>
License: Apache-2.0
Project-URL: Homepage, https://opendev.org/openstack/mistral-tempest-plugin
Project-URL: Repository, https://opendev.org/openstack/mistral-tempest-plugin
Classifier: Environment :: OpenStack
Classifier: Intended Audience :: Information Technology
Classifier: Intended Audience :: System Administrators
Classifier: License :: OSI Approved :: Apache Software License
Classifier: Operating System :: POSIX :: Linux
Classifier: Programming Language :: Python
Classifier: Programming Language :: Python :: 3
Classifier: Programming Language :: Python :: 3.10
Classifier: Programming Language :: Python :: 3.11
Classifier: Programming Language :: Python :: 3.12
Classifier: Programming Language :: Python :: 3.13
Classifier: Programming Language :: Python :: 3 :: Only
Classifier: Programming Language :: Python :: Implementation :: CPython
Requires-Python: >=3.10
License-File: LICENSE
License-File: AUTHORS
Requires-Dist: pbr !=2.1.0,>=2.0.0
Requires-Dist: oslo.concurrency >=3.26.0
Requires-Dist: oslo.config >=5.2.0
Requires-Dist: oslo.utils >=3.33.0
Requires-Dist: oslo.log >=3.36.0
Requires-Dist: oslo.serialization !=2.19.1,>=2.18.0
Requires-Dist: paramiko >=2.0.0
Requires-Dist: tempest >=17.1.0
Requires-Dist: testtools >=2.2.0
Requires-Dist: python-keystoneclient >=3.8.0
